README.md
setup.cfg
setup.py
SQLtime/__init__.py
SQLtime/sqltime.py
SQLtime.egg-info/PKG-INFO
SQLtime.egg-info/SOURCES.txt
SQLtime.egg-info/dependency_links.txt
SQLtime.egg-info/requires.txt
SQLtime.egg-info/top_level.txt