Metadata-Version: 1.1
Name: SQLtime
Version: 1.0
Summary: Python lib to automate time based SQLi
Home-page: https://github.com/nishitm/SQLtime
Author: Nishit
Author-email: nishit@mailfence.com
License: MIT
Download-URL: https://github.com/nishitm/SQLtime/archive/v1.0.tar.gz
Keywords: Blind time based SQL injection,Pentesting,AppSec
Platform: UNKNOWN
Classifier: Development Status :: 4 - Beta
Classifier: Intended Audience :: Developers
Classifier: Topic :: Software Development :: Build Tools
Classifier: License :: OSI Approved :: MIT License
Classifier: Programming Language :: Python :: 3
Classifier: Programming Language :: Python :: 3.4
Classifier: Programming Language :: Python :: 3.5
Classifier: Programming Language :: Python :: 3.6
